bcpandas/__init__.py
bcpandas/constants.py
bcpandas/main.py
bcpandas/utils.py
bcpandas-2.7.2.dist-info/METADATA
bcpandas-2.7.2.dist-info/WHEEL
bcpandas-2.7.2.dist-info/entry_points.txt
bcpandas-2.7.2.dist-info/top_level.txt
bcpandas-2.7.2.dist-info/RECORD
