Metadata-Version: 2.1
Name: bcpandas
Version: 2.7.2
Summary: High-level wrapper around BCP for high performance data transfers between pandas and SQL Server. No knowledge of BCP required!!
Author-email: Josh Dimarsky <24758845+yehoshuadimarsky@users.noreply.github.com>
Maintainer-email: Oliver Borchert <me@borchero.com>
License: MIT License
Project-URL: repository, https://github.com/yehoshuadimarsky/bcpandas
Keywords: bcp,mssql,pandas
Classifier: Topic :: Database
Classifier: Intended Audience :: Developers
Classifier: License :: OSI Approved :: MIT License
Classifier: Operating System :: OS Independent
Classifier: Programming Language :: Python :: 3.9
Classifier: Programming Language :: Python :: 3.10
Classifier: Programming Language :: Python :: 3.11
Classifier: Programming Language :: Python :: 3.12
Classifier: Programming Language :: Python :: 3.13
Classifier: Programming Language :: SQL
Requires-Python: <=3.13,>=3.9
Requires-Dist: pandas[sql-other]>=2.2; python_version >= "3.12"
Requires-Dist: pandas[sql-other]<2.2,>=2.1.2; python_version >= "3.9" and python_version <= "3.11"
Requires-Dist: pyodbc>=5.2; python_version >= "3.13"
Requires-Dist: pyodbc>=5; python_version <= "3.12"
Requires-Dist: sqlalchemy>=1.4; python_version <= "3.12"
Requires-Dist: sqlalchemy>=2.0.31; python_version >= "3.13"
